<?xml version="1.0" encoding="utf-8"?>
<gameobjects>

<brick><name>brick1</name><width>82</width><height>26</height><x>279</x><y>120</y></brick>
<brick><name>brick2</name><width>129</width><height>26</height><x>431.5</x><y>200</y></brick>
<brick><name>brick3</name><width>26</width><height>26</height><x>638</x><y>200</y></brick>
<brick><name>brick4</name><width>26</width><height>26</height><x>715</x><y>200</y></brick>
<brick><name>brick5</name><width>129</width><height>26</height><x>895.5</x><y>200</y></brick>
<brick><name>brick6</name><width>129</width><height>26</height><x>1060.5</x><y>251</y></brick>
<brick><name>brick7</name><width>26</width><height>26</height><x>1023</x><y>120</y></brick>
<brick><name>brick8</name><width>26</width><height>26</height><x>1100</x><y>120</y></brick>
<brick><name>brick9</name><width>129</width><height>26</height><x>1229.5</x><y>200</y></brick>
<brick><name>brick10</name><width>26</width><height>26</height><x>1546</x><y>120</y></brick>
<brick><name>brick11</name><width>26</width><height>26</height><x>1623</x><y>120</y></brick>
<brick><name>brick12</name><width>28</width><height>26</height><x>1702</x><y>120</y></brick>
<brick><name>brick13</name><width>129</width><height>26</height><x>1803.5</x><y>200</y></brick>
<brick><name>brick14</name><width>28</width><height>26</height><x>1932</x><y>200</y></brick>
<brick><name>brick15</name><width>28</width><height>26</height><x>2008</x><y>200</y></brick>
<brick><name>brick16</name><width>28</width><height>26</height><x>2079</x><y>120</y></brick>
<brick><name>brick17</name><width>28</width><height>26</height><x>2158</x><y>133</y></brick>
<brick><name>brick18</name><width>28</width><height>26</height><x>2234</x><y>160</y></brick>
<brick><name>brick19</name><width>28</width><height>26</height><x>2308</x><y>187</y></brick>
<brick><name>brick20</name><width>28</width><height>26</height><x>2659</x><y>120</y></brick>
<brick><name>brick21</name><width>129</width><height>26</height><x>2850.5</x><y>200</y></brick>
<brick><name>brick22</name><width>26</width><height>26</height><x>3062</x><y>120</y></brick>
<brick><name>brick23</name><width>129</width><height>26</height><x>3164.5</x><y>200</y></brick>
<brick><name>brick24</name><width>26</width><height>26</height><x>3339</x><y>161</y></brick>
<brick><name>brick25</name><width>26</width><height>26</height><x>3489</x><y>174</y></brick>
<brick><name>brick26</name><width>26</width><height>26</height><x>3556</x><y>120</y></brick>

</gameobjects>